streamdeck_cli/__init__.py
streamdeck_cli/__main__.py
streamdeck_cli/commands/__init__.py
streamdeck_cli/commands/create.py
streamdeck_cli/commands/validate.py
streamdeck_cli/commands/pack/__init__.py
streamdeck_cli/commands/pack/autoversion.py
streamdeck_cli/commands/pack/zip.py
streamdeck_cli/models/__init__.py
streamdeck_cli/models/manifest.py
streamdeck_cli/utils/_version.py
streamdeck_plugin_sdk_cli-0.1.0.dist-info/LICENSE
streamdeck_plugin_sdk_cli-0.1.0.dist-info/METADATA
streamdeck_plugin_sdk_cli-0.1.0.dist-info/WHEEL
streamdeck_plugin_sdk_cli-0.1.0.dist-info/entry_points.txt
streamdeck_plugin_sdk_cli-0.1.0.dist-info/top_level.txt
streamdeck_plugin_sdk_cli-0.1.0.dist-info/RECORD
