Metadata-Version: 2.2
Name: streamdeck-plugin-sdk-cli
Version: 0.1.0
Summary: CLI util to create the scaffolding of a Stream Deck plugin, validate it, and pack it to be ready for install.
Author-email: strohganoff <you@example.com>
License: MIT License
Project-URL: Homepage, https://github.com/strohganoff/python-streamdeck-plugin-sdk-cli
Project-URL: Repository, https://github.com/strohganoff/python-streamdeck-plugin-sdk-cli
Project-URL: Documentation, https://docs.elgato.com/streamdeck/sdk/introduction/getting-started/
Project-URL: Issues, https://github.com/strohganoff/python-streamdeck-plugin-sdk-cli/issues
Keywords: python,sdk,streamdeck,streamdeck_sdk,streamdeck_plugin_sdk,stream deck,stream deck sdk,stream deck plugin sdk,streamdeck-sdk,streamdeck-plugin-sdk,stream-deck,stream-deck-sdk,stream-deck-plugin-sdk,elgato,elgato sdk,elgato plugin,elgato sdk,elgato stream deck,elgato stream deck sdk,elgato stream deck plugin sdk
Classifier: Intended Audience :: Developers
Classifier: Operating System :: OS Independent
Classifier: Programming Language :: Python :: 3
Classifier: Programming Language :: Python
Classifier: Programming Language :: Python :: 3 :: Only
Classifier: Programming Language :: Python :: 3.9
Classifier: Programming Language :: Python :: 3.10
Classifier: Programming Language :: Python :: 3.11
Classifier: Programming Language :: Python :: 3.12
Classifier: Development Status :: 4 - Beta
Classifier: Environment :: MacOS X
Classifier: Intended Audience :: Developers
Classifier: License :: OSI Approved :: MIT License
Classifier: Topic :: Software Development :: Libraries :: Application Frameworks
Classifier: Topic :: Software Development :: Libraries :: Python Modules
Classifier: Typing :: Typed
Requires-Python: >=3.9
License-File: LICENSE
Requires-Dist: copier>=9.4.1
Requires-Dist: pathspec>=0.12.1
Requires-Dist: pydantic>=2.9.2
Requires-Dist: pydantic_core>=2.23.4
Requires-Dist: typer>=0.12.5
Provides-Extra: dev
Requires-Dist: pytest>=8.3.3; extra == "dev"
Requires-Dist: pytest-cov>=5.0.0; extra == "dev"
Requires-Dist: pytest-mock>=3.14.0; extra == "dev"
Requires-Dist: pytest-sugar>=1.0.0; extra == "dev"
Requires-Dist: tox>=4.23.2; extra == "dev"
